djet/__init__.py
djet/assertions.py
djet/files.py
djet/restframework.py
djet/testcases.py
djet-0.3.0.dist-info/LICENSE
djet-0.3.0.dist-info/METADATA
djet-0.3.0.dist-info/WHEEL
djet-0.3.0.dist-info/top_level.txt
djet-0.3.0.dist-info/RECORD
