Metadata-Version: 2.1
Name: djet
Version: 0.3.0
Summary: Set of helpers for easy testing of Django apps.
Home-page: https://github.com/sunscrapers/djet
Author: SUNSCRAPERS
Author-email: info@sunscrapers.com
License: MIT
Platform: UNKNOWN
Classifier: Development Status :: 3 - Alpha
Classifier: Environment :: Web Environment
Classifier: Framework :: Django
Classifier: Intended Audience :: Developers
Classifier: License :: OSI Approved :: MIT License
Classifier: Operating System :: OS Independent
Classifier: Programming Language :: Python
Classifier: Programming Language :: Python :: 3
Classifier: Topic :: Software Development :: Testing
License-File: LICENSE
